{
  "interval": {
    "intervalStart": "2025-03-30T00:00:00.000Z",
    "intervalEnd": "2025-04-06T00:00:00.000Z",
    "intervalType": "week"
  },
  "repository": "elizaos/eliza",
  "overview": "From 2025-03-30 to 2025-04-06, elizaos/eliza had 7 new PRs (1 merged), 2 new issues, and 11 active contributors.",
  "topIssues": [
    {
      "id": "I_kwDOMT5cIs6wuTSy",
      "title": "chore: Test every command in docs cli section",
      "author": "madjin",
      "number": 4143,
      "repository": "elizaos/eliza",
      "createdAt": "2025-04-02T01:52:19Z",
      "closedAt": null,
      "state": "OPEN",
      "commentCount": 0
    },
    {
      "id": "I_kwDOMT5cIs6w2eyG",
      "title": "How to run Eliza CLI?",
      "author": "LinuxIsCool",
      "number": 4159,
      "repository": "elizaos/eliza",
      "createdAt": "2025-04-02T17:20:34Z",
      "closedAt": null,
      "state": "OPEN",
      "commentCount": 0
    }
  ],
  "topPRs": [
    {
      "id": "PR_kwDOMT5cIs6RTkjF",
      "title": "feat: Test Coverage for plugin-bootstrap",
      "author": "HarshModi2005",
      "number": 4173,
      "repository": "elizaos/eliza",
      "createdAt": "2025-04-03T19:08:50Z",
      "mergedAt": "2025-04-05T19:12:35Z",
      "additions": 12160,
      "deletions": 25
    },
    {
      "id": "PR_kwDOMT5cIs6RdhrX",
      "title": "feat: Add 100% instrumentation coverage for Twitter plugin",
      "author": "Imsharad",
      "number": 4190,
      "repository": "elizaos/eliza",
      "createdAt": "2025-04-04T21:17:12Z",
      "mergedAt": null,
      "additions": 2252,
      "deletions": 101
    },
    {
      "id": "PR_kwDOMT5cIs6RhGP0",
      "title": "initial commit for fixing delete character button",
      "author": "Y4NK33420",
      "number": 4197,
      "repository": "elizaos/eliza",
      "createdAt": "2025-04-05T22:50:12Z",
      "mergedAt": "2025-04-09T15:23:53Z",
      "additions": 791,
      "deletions": 111
    },
    {
      "id": "PR_kwDOMT5cIs6Rb77V",
      "title": "fix: Eli2 134/make npm create eliza and npx elizaos create functionally identical",
      "author": "yungalgo",
      "number": 4185,
      "repository": "elizaos/eliza",
      "createdAt": "2025-04-04T16:44:18Z",
      "mergedAt": "2025-04-08T09:48:42Z",
      "additions": 213,
      "deletions": 9
    },
    {
      "id": "PR_kwDOMT5cIs6Rb9k4",
      "title": "feat: Add message buttons",
      "author": "ncale",
      "number": 4187,
      "repository": "elizaos/eliza",
      "createdAt": "2025-04-04T16:48:48Z",
      "mergedAt": "2025-04-10T11:18:52Z",
      "additions": 87,
      "deletions": 4
    }
  ],
  "codeChanges": {
    "additions": 22619,
    "deletions": 3509,
    "files": 16,
    "commitCount": 24
  },
  "completedItems": [
    {
      "title": "feat: Test Coverage for plugin-bootstrap",
      "prNumber": 4173,
      "type": "feature"
    }
  ],
  "topContributors": [
    {
      "username": "HarshModi2005",
      "pr_count": 1,
      "issue_count": 0,
      "review_count": 7
    },
    {
      "username": "monilpat",
      "pr_count": 0,
      "issue_count": 0,
      "review_count": 5
    },
    {
      "username": "0xbbjoker",
      "pr_count": 1,
      "issue_count": 0,
      "review_count": 0
    },
    {
      "username": "Imsharad",
      "pr_count": 1,
      "issue_count": 0,
      "review_count": 0
    },
    {
      "username": "Y4NK33420",
      "pr_count": 1,
      "issue_count": 0,
      "review_count": 0
    }
  ],
  "newPRs": 7,
  "mergedPRs": 1,
  "newIssues": 2,
  "closedIssues": 0,
  "activeContributors": 11
}